gymnesium/__init__.py
gymnesium/_rom.py
gymnesium/gymnesium.py
gymnesium-0.1.7.dist-info/LICENSE.txt
gymnesium-0.1.7.dist-info/METADATA
gymnesium-0.1.7.dist-info/WHEEL
gymnesium-0.1.7.dist-info/top_level.txt
gymnesium-0.1.7.dist-info/RECORD
