Metadata-Version: 2.1
Name: gymnesium
Version: 0.1.7
Summary: An NES Gymnasium Environment
Home-page: https://github.com/Hal609/GymNESium
Author: Hal Kolb
Author-email: hal@kolb.co.uk
License: MIT
Keywords: NES Emulator OpenAI-Gym Gymnasium Reinforcement-Learning-Environment
Classifier: Development Status :: 5 - Production/Stable
Classifier: Intended Audience :: Developers
Classifier: Intended Audience :: Science/Research
Classifier: License :: OSI Approved :: MIT License
Classifier: Operating System :: MacOS :: MacOS X
Classifier: Operating System :: POSIX :: Linux
Classifier: Operating System :: Microsoft :: Windows
Classifier: Programming Language :: C++
Classifier: Programming Language :: Python :: 3 :: Only
Classifier: Programming Language :: Python :: 3.5
Classifier: Programming Language :: Python :: 3.6
Classifier: Programming Language :: Python :: 3.7
Classifier: Programming Language :: Python :: 3.8
Classifier: Programming Language :: Python :: 3.9
Classifier: Programming Language :: Python :: 3.10
Classifier: Programming Language :: Python :: 3.11
Classifier: Programming Language :: Python :: 3.12
Classifier: Topic :: Games/Entertainment
Classifier: Topic :: Software Development :: Libraries :: Python Modules
Classifier: Topic :: System :: Emulators
License-File: LICENSE.txt
Requires-Dist: numpy>=1.18.5
Requires-Dist: cynes>=0.1.0
Requires-Dist: gymnasium>=1.0.0
Requires-Dist: pysdl2
Requires-Dist: pysdl2-dll
